luigi_neo4j_target/__init__.py
luigi_neo4j_target/graph.py
luigi_neo4j_target/target.py
luigi_neo4j_target-1.1.0.dist-info/LICENSE
luigi_neo4j_target-1.1.0.dist-info/METADATA
luigi_neo4j_target-1.1.0.dist-info/WHEEL
luigi_neo4j_target-1.1.0.dist-info/top_level.txt
luigi_neo4j_target-1.1.0.dist-info/RECORD
