Metadata-Version: 2.1
Name: luigi-neo4j-target
Version: 1.1.0
Summary: A Luigi Target implementation for Neo4j.
Author-email: Pawel Gasiorowski <p.gasiorowski@axent.pl>
License: Apache License
Project-URL: Homepage, https://github.com/axent-pl/luigi-neo4j-target
Project-URL: Bug Tracker, https://github.com/axent-pl/luigi-neo4j-target/issues
Keywords: luigi,neo4j,target
Classifier: Programming Language :: Python :: 3
Classifier: License :: OSI Approved :: Apache Software License
Classifier: Operating System :: OS Independent
Requires-Python: >=3.6
License-File: LICENSE
Requires-Dist: luigi
Requires-Dist: neo4j
